node_graph/__init__.py
node_graph/analysis.py
node_graph/cli.py
node_graph/collection.py
node_graph/config.py
node_graph/decorator.py
node_graph/error_handler.py
node_graph/errors.py
node_graph/executor.py
node_graph/graph.py
node_graph/link.py
node_graph/manager.py
node_graph/materialize.py
node_graph/mixins.py
node_graph/property.py
node_graph/registry.py
node_graph/semantics.py
node_graph/serializer.py
node_graph/socket.py
node_graph/socket_meta.py
node_graph/socket_spec.py
node_graph/task.py
node_graph/task_spec.py
node_graph/engine/__init__.py
node_graph/engine/base.py
node_graph/engine/local.py
node_graph/engine/provenance.py
node_graph/engine/utils.py
node_graph/executors/__init__.py
node_graph/executors/tests.py
node_graph/knowledge/__init__.py
node_graph/knowledge/graph.py
node_graph/knowledge/visualization.py
node_graph/orm/__init__.py
node_graph/orm/mapping.py
node_graph/properties/__init__.py
node_graph/properties/builtins.py
node_graph/sockets/__init__.py
node_graph/sockets/builtins.py
node_graph/tasks/__init__.py
node_graph/tasks/builtins.py
node_graph/tasks/function_task.py
node_graph/tasks/subgraph_task.py
node_graph/tasks/task_pool.py
node_graph/tasks/tests.py
node_graph/utils/__init__.py
node_graph/utils/function.py
node_graph/utils/graph.py
node_graph/utils/json_utils.py
node_graph/utils/struct_utils.py
node_graph-0.6.5.dist-info/entry_points.txt
node_graph-0.6.5.dist-info/licenses/LICENSE
node_graph-0.6.5.dist-info/WHEEL
node_graph-0.6.5.dist-info/METADATA
node_graph-0.6.5.dist-info/RECORD
