Metadata-Version: 2.4
Name: node_graph
Version: 0.6.5
Summary: Create node-based workflow
Keywords: graph,workflows
Author-email: Xing Wang <xingwang1991@gmail.com>
Requires-Python: >=3.10
Classifier: Development Status :: 1 - Planning
Classifier: License :: OSI Approved :: MIT License
Classifier: Operating System :: POSIX :: Linux
Classifier: Operating System :: MacOS :: MacOS X
Classifier: Programming Language :: Python
Classifier: Programming Language :: Python :: 3.10
Classifier: Programming Language :: Python :: 3.11
Classifier: Programming Language :: Python :: 3.12
Classifier: Topic :: Scientific/Engineering
License-File: LICENSE
Requires-Dist: numpy
Requires-Dist: scipy
Requires-Dist: cloudpickle
Requires-Dist: node-graph-widget
Requires-Dist: wrapt
Requires-Dist: pydantic~=2.6
Requires-Dist: typing_extensions
Requires-Dist: pyyaml
Requires-Dist: rdflib>=6.0
Requires-Dist: graphviz>=0.20
Requires-Dist: click>=8.1
Requires-Dist: sphinx_rtd_theme ; extra == "docs"
Requires-Dist: sphinx~=7.2 ; extra == "docs"
Requires-Dist: nbsphinx ; extra == "docs"
Requires-Dist: pre-commit~=2.2 ; extra == "pre-commit"
Requires-Dist: pylint~=2.17.4 ; extra == "pre-commit"
Requires-Dist: pytest~=7.0 ; extra == "tests"
Requires-Dist: pytest-cov~=2.7,<2.11 ; extra == "tests"
Requires-Dist: pytest-asyncio ; extra == "tests"
Project-URL: Documentation, https://node-graph.readthedocs.io
Project-URL: Source, https://github.com/scinode/node-graph
Provides-Extra: docs
Provides-Extra: pre-commit
Provides-Extra: tests
